solace_semp_config/__init__.py
solace_semp_config/api_client.py
solace_semp_config/configuration.py
solace_semp_config/rest.py
solace_semp_config/api/__init__.py
solace_semp_config/api/about_api.py
solace_semp_config/api/acl_profile_api.py
solace_semp_config/api/all_api.py
solace_semp_config/api/authentication_oauth_provider_api.py
solace_semp_config/api/authorization_group_api.py
solace_semp_config/api/bridge_api.py
solace_semp_config/api/cert_authority_api.py
solace_semp_config/api/client_cert_authority_api.py
solace_semp_config/api/client_profile_api.py
solace_semp_config/api/client_username_api.py
solace_semp_config/api/distributed_cache_api.py
solace_semp_config/api/dmr_bridge_api.py
solace_semp_config/api/dmr_cluster_api.py
solace_semp_config/api/domain_cert_authority_api.py
solace_semp_config/api/jndi_api.py
solace_semp_config/api/mqtt_retain_cache_api.py
solace_semp_config/api/mqtt_session_api.py
solace_semp_config/api/msg_vpn_api.py
solace_semp_config/api/queue_api.py
solace_semp_config/api/queue_template_api.py
solace_semp_config/api/replay_log_api.py
solace_semp_config/api/replicated_topic_api.py
solace_semp_config/api/rest_delivery_point_api.py
solace_semp_config/api/system_information_api.py
solace_semp_config/api/topic_endpoint_api.py
solace_semp_config/api/topic_endpoint_template_api.py
solace_semp_config/api/virtual_hostname_api.py
solace_semp_config/models/__init__.py
solace_semp_config/models/about.py
solace_semp_config/models/about_api.py
solace_semp_config/models/about_api_links.py
solace_semp_config/models/about_api_response.py
solace_semp_config/models/about_links.py
solace_semp_config/models/about_response.py
solace_semp_config/models/about_user.py
solace_semp_config/models/about_user_links.py
solace_semp_config/models/about_user_msg_vpn.py
solace_semp_config/models/about_user_msg_vpn_links.py
solace_semp_config/models/about_user_msg_vpn_response.py
solace_semp_config/models/about_user_msg_vpns_response.py
solace_semp_config-9.8.0.12.dist-info/METADATA
solace_semp_config-9.8.0.12.dist-info/WHEEL
solace_semp_config-9.8.0.12.dist-info/top_level.txt
solace_semp_config-9.8.0.12.dist-info/RECORD
